{
  "red_fighter": "Bruno Silva",
  "blue_fighter": "Charles Johnson",
  "predicted_winner": "Bruno Silva",
  "prediction_code": 0,
  "confidence": "96.8%",
  "confidence_value": 0.9675925925925926,
  "red_win_probability": "96.8%",
  "red_win_probability_value": 0.9675925925925926,
  "blue_win_probability": "3.2%",
  "blue_win_probability_value": 0.03240740740740744,
  "timestamp": "2026-03-11 16:41:47",
  "input_schema": "ufc_profile_aligned_v2",
  "probability_method": "corner_swap_averaged",
  "reasoning_summary": "Model leans toward Red corner mainly due to: Recent Win Rate, Reliability-Adjusted Significant Strikes Absorbed Per Minute, Reliability-Adjusted Takedowns Landed Per 15 Minutes.",
  "reasoning": [
    {
      "feature": "delta_recent_win_rate",
      "label": "Recent Win Rate",
      "importance": 0.3870382554103582,
      "value": 0.5,
      "baseline": 0.05496453900709221,
      "z_score": 0.49077333762449216,
      "signed_impact": 0.18994805639610216,
      "favors": "red"
    },
    {
      "feature": "delta_shrunk_sapm",
      "label": "Reliability-Adjusted Significant Strikes Absorbed Per Minute",
      "importance": 0.020807544718644853,
      "value": 0.4569117647058816,
      "baseline": -0.07060887662848711,
      "z_score": 0.3806388595000444,
      "signed_impact": 0.007920160090701149,
      "favors": "red"
    },
    {
      "feature": "delta_shrunk_td_avg",
      "label": "Reliability-Adjusted Takedowns Landed Per 15 Minutes",
      "importance": 0.007418591952400231,
      "value": 1.3205882352941176,
      "baseline": 0.11312728257591573,
      "z_score": 0.786475948102806,
      "signed_impact": 0.005834544139351818,
      "favors": "red"
    },
    {
      "feature": "delta_shrunk_td_acc",
      "label": "Reliability-Adjusted Takedown Accuracy",
      "importance": 0.025664369492904113,
      "value": 0.0701470588235294,
      "baseline": 0.02912622543494911,
      "z_score": 0.20441783259560012,
      "signed_impact": 0.0052462547866720995,
      "favors": "red"
    },
    {
      "feature": "delta_draws",
      "label": "Career Draws",
      "importance": 0.0014992019796151409,
      "value": 2.0,
      "baseline": 0.04609929078014184,
      "z_score": 3.4835959409638377,
      "signed_impact": 0.005222613930872255,
      "favors": "red"
    }
  ],
  "explainability_note": "Feature-importance heuristic explanation (not causal proof)."
}